windows_tools.bitness-0.2.1-py3.12-nspkg.pth
windows_tools/bitness/__init__.py
windows_tools.bitness-0.2.1.dist-info/LICENSE
windows_tools.bitness-0.2.1.dist-info/METADATA
windows_tools.bitness-0.2.1.dist-info/WHEEL
windows_tools.bitness-0.2.1.dist-info/namespace_packages.txt
windows_tools.bitness-0.2.1.dist-info/top_level.txt
windows_tools.bitness-0.2.1.dist-info/RECORD
